LICENSE.txt
MANIFEST.in
README.rst
setup.py
django_sitepush.egg-info/PKG-INFO
django_sitepush.egg-info/SOURCES.txt
django_sitepush.egg-info/dependency_links.txt
django_sitepush.egg-info/requires.txt
django_sitepush.egg-info/top_level.txt
sitepush/__init__.py
sitepush/management/__init__.py
sitepush/management/commands/__init__.py
sitepush/management/commands/deploy_local.py
sitepush/management/commands/deploy_remote.py