Metadata-Version: 1.0
Name: django-sitepush
Version: 0.0.1dev3
Summary: Redeploy Django projects using management commands
Home-page: http://github.com/yprez/django-sitepush
Author: Yuri Prezument
Author-email: y@yprez.com
License: ISC
Platform: UNKNOWN
Classifier: Development Status :: 2 - Pre-Alpha
Classifier: Framework :: Django
Classifier: Intended Audience :: Developers
Classifier: Natural Language :: English
Classifier: License :: OSI Approved :: ISC License (ISCL)
Classifier: Programming Language :: Python
Classifier: Programming Language :: Python :: 2.6
Classifier: Programming Language :: Python :: 2.7
